parallel_apply/__init__.py
parallel_apply-0.1.1.dist-info/WHEEL
parallel_apply-0.1.1.dist-info/METADATA
parallel_apply-0.1.1.dist-info/RECORD
